edc_form_validators/__init__.py
edc_form_validators/applicable_field_validator.py
edc_form_validators/apps.py
edc_form_validators/base_form_validator.py
edc_form_validators/current_site_validator.py
edc_form_validators/date_range_validator.py
edc_form_validators/date_validator.py
edc_form_validators/exceptions.py
edc_form_validators/form_validator.py
edc_form_validators/form_validator_mixin.py
edc_form_validators/form_validator_mixins.py
edc_form_validators/locale_validator.py
edc_form_validators/many_to_many_field_validator.py
edc_form_validators/other_specify_field_validator.py
edc_form_validators/range_field_validator.py
edc_form_validators/required_field_validator.py
edc_form_validators/test_case_mixin.py
edc_form_validators/urls.py
edc_form_validators/extra_mixins/__init__.py
edc_form_validators/extra_mixins/study_day_form_validator.py
edc_form_validators/tests/__init__.py
edc_form_validators/tests/mixins.py
edc_form_validators/tests/test_applicable.py
edc_form_validators/tests/test_dates.py
edc_form_validators/tests/test_endpoints.py
edc_form_validators/tests/test_m2m_validators.py
edc_form_validators/tests/test_modelform_validators.py
edc_form_validators/tests/test_not_required.py
edc_form_validators/tests/test_other_specify.py
edc_form_validators/tests/test_out_of_range.py
edc_form_validators/tests/test_required.py
edc_form_validators/tests/test_settings.py
edc_form_validators/tests/etc/user-aes-local.key
edc_form_validators/tests/etc/user-aes-restricted.key
edc_form_validators/tests/etc/user-rsa-local-private.pem
edc_form_validators/tests/etc/user-rsa-local-public.pem
edc_form_validators/tests/etc/user-rsa-restricted-private.pem
edc_form_validators/tests/etc/user-rsa-restricted-public.pem
edc_form_validators/tests/etc/user-salt-local.key
edc_form_validators/tests/etc/user-salt-restricted.key
form_validators_app/__init__.py
form_validators_app/admin.py
form_validators_app/apps.py
form_validators_app/forms.py
form_validators_app/models.py
edc_form_validators-1.0.0.dist-info/AUTHORS
edc_form_validators-1.0.0.dist-info/LICENSE
edc_form_validators-1.0.0.dist-info/METADATA
edc_form_validators-1.0.0.dist-info/WHEEL
edc_form_validators-1.0.0.dist-info/top_level.txt
edc_form_validators-1.0.0.dist-info/RECORD
